connections.py
setup.py
connections.egg-info/PKG-INFO
connections.egg-info/SOURCES.txt
connections.egg-info/dependency_links.txt
connections.egg-info/top_level.txt