Metadata-Version: 1.1
Name: connections
Version: 0.1.2
Summary: Universal Connection Pool
Home-page: http://github.com/operetta/connections
Author: operetta
Author-email: eric@sunshake.com
License: Apache License, Version 2.0
Keywords: connection,pool,retry,states,waiting
Platform: UNKNOWN
Classifier: Development Status :: 4 - Beta
Classifier: Intended Audience :: Developers
Classifier: License :: OSI Approved :: Apache Software License
Classifier: Programming Language :: Python
Classifier: Operating System :: OS Independent
Classifier: Topic :: Software Development :: Libraries :: Python Modules
